typing_extensions.py
typing_extensions-3.10.0.1.dist-info/LICENSE
typing_extensions-3.10.0.1.dist-info/METADATA
typing_extensions-3.10.0.1.dist-info/WHEEL
typing_extensions-3.10.0.1.dist-info/top_level.txt
typing_extensions-3.10.0.1.dist-info/RECORD
