Metadata-Version: 2.1
Name: typing_extensions
Version: 3.10.0.1
Summary: Backported and Experimental Type Hints for Python 3.5+
Home-page: https://github.com/python/typing/blob/master/typing_extensions/README.rst
Author: Guido van Rossum, Jukka Lehtosalo, Łukasz Langa, Michael Lee
Author-email: levkivskyi@gmail.com
License: PSF
Keywords: typing function annotations type hints hinting checking checker typehints typehinting typechecking backport
Platform: UNKNOWN
Classifier: Development Status :: 3 - Alpha
Classifier: Environment :: Console
Classifier: Intended Audience :: Developers
Classifier: License :: OSI Approved :: Python Software Foundation License
Classifier: Operating System :: OS Independent
Classifier: Programming Language :: Python :: 2.7
Classifier: Programming Language :: Python :: 3.4
Classifier: Programming Language :: Python :: 3.5
Classifier: Programming Language :: Python :: 3.6
Classifier: Programming Language :: Python :: 3.7
Classifier: Programming Language :: Python :: 3.8
Classifier: Programming Language :: Python :: 3.9
Classifier: Programming Language :: Python :: 3.10
Classifier: Topic :: Software Development
License-File: LICENSE
